README
ez_setup.py
setup.py
webstring/__init__.py
webstring/base.py
webstring/etreet.py
webstring/html.py
webstring/htmlbase.py
webstring/lxmlt.py
webstring/text.py
webstring/wsgi.py
webstring/xmlbase.py
webstring/xmlt.py
webstring.egg-info/PKG-INFO
webstring.egg-info/SOURCES.txt
webstring.egg-info/dependency_links.txt
webstring.egg-info/entry_points.txt
webstring.egg-info/requires.txt
webstring.egg-info/top_level.txt
webstring.egg-info/zip-safe
webstring/docs/CHANGELOG-0.5
webstring/docs/seceaddr.gif
webstring/docs/text.html
webstring/docs/webstring.css
webstring/docs/webstring.gif
webstring/docs/webstring.html
webstring/ext/__init__.py
webstring/ext/turbogears.py
webstring/tests/__init__.py
webstring/tests/doctest_lwebstring.py
webstring/tests/doctest_text.py
webstring/tests/doctest_webstring.py
webstring/tests/test_lwebstring.py
webstring/tests/test_text.py
webstring/tests/test_webstring.py
