Metadata-Version: 1.0
Name: webstring
Version: 0.5
Summary: Template engine that uses Python as the template language
Home-page: http://psilib.sourceforge.net/webstring.html
Author: L. C. Rees
Author-email: lcrees@gmail.com
License: BSD
Keywords: template text XML HTML XHTML meld TurboGears WSGI
Platform: UNKNOWN
Classifier: Development Status :: 4 - Beta
Classifier: Environment :: Web Environment
Classifier: Intended Audience :: Developers
Classifier: Framework :: TurboGears
Classifier: License :: OSI Approved :: BSD License
Classifier: Natural Language :: English
Classifier: Operating System :: OS Independent
Classifier: Programming Language :: Python
Classifier: Topic :: Internet :: WWW/HTTP
Classifier: Topic :: Internet :: WWW/HTTP :: Dynamic Content
Classifier: Topic :: Text Processing
Classifier: Topic :: Text Processing :: Markup :: HTML
Classifier: Topic :: Text Processing :: Markup :: XML
